<poema>

<texto verso="Gato que brincas na rua" ordem="1,3,5" taxon="verso1,verso2,verso3"></texto>
<texto verso="Como se fosse na cama" ordem="5" taxon="verso4"></texto>
<texto verso="Invejo a sorte que é tua" ordem="3" taxon="verso3"></texto>
<texto verso="Porque nem sorte se chama" ordem="3" taxon="verso3"></texto>
<texto verso="*" ordem="1" taxon="verso5"></texto>

<categorias>

        <verso1>
                <frase>Rato</frase>
                <frase>Gato</frase>
                <frase>Sapo</frase>
                <frase>Sapato</frase>
        </verso1>

        <verso2>
                <frase>corres</frase>
                <frase>saltas</frase>
                <frase>róis</frase>
                <frase>comes</frase>
                <frase>descansas</frase>
        </verso2>

        <verso3>
                <frase>lua</frase>
                <frase>água</frase>
                <frase>terra</frase>
                <frase>rua</frase>
                <frase>grua</frase>
        </verso3>

         <verso4>
                <frase>lama</frase>
                <frase>chama</frase>
                <frase>cama</frase>
                <frase>rama</frase>
                <frase>grama</frase>
        </verso4>       
        <verso5>
                <frase> </frase>                
        </verso5>       

</categorias>

</poema>